tox_constraints/__init__.py
tox_constraints/hooks.py
tox_constraints-0.14.1.dist-info/LICENSE
tox_constraints-0.14.1.dist-info/METADATA
tox_constraints-0.14.1.dist-info/WHEEL
tox_constraints-0.14.1.dist-info/entry_points.txt
tox_constraints-0.14.1.dist-info/top_level.txt
tox_constraints-0.14.1.dist-info/RECORD
