Metadata-Version: 2.1
Name: tox-constraints
Version: 0.14.1
Summary: Reproducible tests, by default.
Home-page: https://github.com/apljungquist/tox-constraints
Author: AP Ljungquist
Author-email: ap@ljungquist.eu
Classifier: License :: OSI Approved :: MIT License
License-File: LICENSE
Requires-Dist: toml
Requires-Dist: tox (>=3.10)
Requires-Dist: virtualenv (>20)
